defern/__about__.py
defern/__init__.py
defern/defern.py
defern-1.0.0.dist-info/LICENSE
defern-1.0.0.dist-info/METADATA
defern-1.0.0.dist-info/WHEEL
defern-1.0.0.dist-info/top_level.txt
defern-1.0.0.dist-info/RECORD
