Metadata-Version: 2.1
Name: defern
Version: 1.0.0
Summary: Provides Go-like `defer`
Home-page: https://github.com/nagataaaas/defern
Author: Yamato Nagata
Author-email: nagata@mail.nagata.pro
License: MIT
Platform: any
Classifier: Development Status :: 4 - Beta
Classifier: Environment :: Other Environment
Classifier: Intended Audience :: Developers
Classifier: License :: OSI Approved :: MIT License
Classifier: Operating System :: OS Independent
Classifier: Programming Language :: Python :: 3
Classifier: Programming Language :: Python
Classifier: Topic :: Software Development :: Libraries :: Python Modules
License-File: LICENSE
